afasi/__init__.py
afasi/__main__.py
afasi/afasi.py
afasi/cli.py
afasi/tabel.py
afasi-2022.11.28.dist-info/LICENSE
afasi-2022.11.28.dist-info/METADATA
afasi-2022.11.28.dist-info/WHEEL
afasi-2022.11.28.dist-info/entry_points.txt
afasi-2022.11.28.dist-info/top_level.txt
afasi-2022.11.28.dist-info/RECORD
