Metadata-Version: 2.1
Name: afasi
Version: 2022.11.28
Summary: Fuzz a language by mixing up only few words.
Author-email: Stefan Hagen <stefan@hagen.link>
Maintainer-email: Stefan Hagen <stefan@hagen.link>
Project-URL: Homepage, https://git.sr.ht/~sthagen/afasi
Project-URL: Bug-Tracker, https://todo.sr.ht/~sthagen/afasi
Project-URL: Documentation, https://codes.dilettant.life/docs/afasi
Project-URL: Source-Code, https://git.sr.ht/~sthagen/afasi
Project-URL: Test-Coverage, https://codes.dilettant.life/coverage/afasi
Keywords: command-line,developer-tools,language-files,patch
Classifier: Development Status :: 4 - Beta
Classifier: Intended Audience :: Developers
Classifier: License :: OSI Approved :: MIT License
Classifier: Programming Language :: Python :: 3.10
Classifier: Programming Language :: Python :: 3.11
Requires-Python: >=3.10
License-File: LICENSE
Requires-Dist: PyYAML (>=6.0)
Requires-Dist: typer (>=0.7.0)
Provides-Extra: dev
Requires-Dist: black ; extra == 'dev'
Requires-Dist: coverage ; extra == 'dev'
Requires-Dist: flake8 ; extra == 'dev'
Requires-Dist: hypothesis ; extra == 'dev'
Requires-Dist: mypy ; extra == 'dev'
Requires-Dist: pytest ; extra == 'dev'
Requires-Dist: pytest-cov ; extra == 'dev'
Requires-Dist: pytest-flake8 ; extra == 'dev'
